benchmarks/__init__.py
benchmarks/cmp_NA19240.py
benchmarks/eval_sim.py
benchmarks/eval_trio.py
benchmarks/multi_platform.py
benchmarks/sta_venn.py
benchmarks/vcf2bedpe.py
cuteSV/CommandRunner.py
cuteSV/__init__.py
cuteSV/cuteSV_Description.py
cuteSV/cuteSV_forcecalling.py
cuteSV/cuteSV_genotype.py
cuteSV/cuteSV_resolveDUP.py
cuteSV/cuteSV_resolveINDEL.py
cuteSV/cuteSV_resolveINV.py
cuteSV/cuteSV_resolveTRA.py
cuteSV/diploid_calling.py
cuteSV-2.0.2.data/data/LICENSE
cuteSV-2.0.2.data/scripts/cuteSV
cuteSV-2.0.2.dist-info/LICENSE
cuteSV-2.0.2.dist-info/METADATA
cuteSV-2.0.2.dist-info/WHEEL
cuteSV-2.0.2.dist-info/top_level.txt
cuteSV-2.0.2.dist-info/RECORD
