Metadata-Version: 2.1
Name: cuteSV
Version: 2.0.2
Summary: Long-read-based human genomic structural variation detection with cuteSV
Home-page: https://github.com/tjiangHIT/cuteSV
Author: Jiang Tao
Author-email: tjiang@hit.edu.cn
License: MIT
License-File: LICENSE
Requires-Dist: pysam
Requires-Dist: Biopython
Requires-Dist: Cigar
Requires-Dist: numpy
Requires-Dist: pyvcf
